pyccolo/__init__.py
pyccolo/__main__.py
pyccolo/_version.py
pyccolo/ast_bookkeeping.py
pyccolo/ast_rewriter.py
pyccolo/emit_event.py
pyccolo/expr_rewriter.py
pyccolo/extra_builtins.py
pyccolo/handler.py
pyccolo/import_hooks.py
pyccolo/predicate.py
pyccolo/py.typed
pyccolo/stmt_inserter.py
pyccolo/stmt_mapper.py
pyccolo/syntax_augmentation.py
pyccolo/trace_events.py
pyccolo/trace_stack.py
pyccolo/tracer.py
pyccolo/utils.py
pyccolo/version.py
pyccolo/_fast/__init__.py
pyccolo/_fast/fast_ast.py
pyccolo/_fast/misc_ast_utils.py
pyccolo/examples/__init__.py
pyccolo/examples/coverage.py
pyccolo/examples/future_tracer.py
pyccolo/examples/lazy_imports.py
pyccolo/examples/optional_chaining.py
pyccolo/examples/pipeline_tracer.py
pyccolo/examples/quasiquote.py
pyccolo/examples/quick_lambda.py
pyccolo/fast/__init__.py
pyccolo/fast/__init__.pyi
pyccolo-0.0.85.dist-info/licenses/docs/LICENSE.txt
pyccolo-0.0.85.dist-info/METADATA
pyccolo-0.0.85.dist-info/WHEEL
pyccolo-0.0.85.dist-info/entry_points.txt
pyccolo-0.0.85.dist-info/top_level.txt
pyccolo-0.0.85.dist-info/RECORD
