Metadata-Version: 2.4
Name: pyccolo
Version: 0.0.85
Summary: Declarative instrumentation for Python
Home-page: https://github.com/smacke/pyccolo
Author: Stephen Macke
Author-email: stephen.macke@gmail.com
License: BSD-3-Clause
Classifier: Development Status :: 3 - Alpha
Classifier: Intended Audience :: Developers
Classifier: License :: OSI Approved :: BSD License
Classifier: Natural Language :: English
Classifier: Programming Language :: Python :: 3.6
Classifier: Programming Language :: Python :: 3.7
Classifier: Programming Language :: Python :: 3.8
Classifier: Programming Language :: Python :: 3.9
Classifier: Programming Language :: Python :: 3.10
Classifier: Programming Language :: Python :: 3.11
Classifier: Programming Language :: Python :: 3.12
Classifier: Programming Language :: Python :: 3.13
Classifier: Programming Language :: Python :: 3.14
Requires-Python: >=3.6
License-File: docs/LICENSE.txt
Requires-Dist: traitlets
Requires-Dist: typing_extensions
Provides-Extra: test
Requires-Dist: black; extra == "test"
Requires-Dist: hypothesis; extra == "test"
Requires-Dist: isort; extra == "test"
Requires-Dist: mypy; extra == "test"
Requires-Dist: pytest; extra == "test"
Requires-Dist: pytest-cov; extra == "test"
Requires-Dist: ruff==0.1.9; extra == "test"
Provides-Extra: dev
Requires-Dist: build; extra == "dev"
Requires-Dist: pycln; extra == "dev"
Requires-Dist: twine; extra == "dev"
Requires-Dist: versioneer; extra == "dev"
Requires-Dist: black; extra == "dev"
Requires-Dist: hypothesis; extra == "dev"
Requires-Dist: isort; extra == "dev"
Requires-Dist: mypy; extra == "dev"
Requires-Dist: pytest; extra == "dev"
Requires-Dist: pytest-cov; extra == "dev"
Requires-Dist: ruff==0.1.9; extra == "dev"
Dynamic: license-file
